MANIFEST.in
README.rst
setup.py
docs/.gitattributes
docs/HISTORY.txt
docs/LICENSE.GPL
docs/LICENSE.txt
ftw/__init__.py
ftw.raven.egg-info/PKG-INFO
ftw.raven.egg-info/SOURCES.txt
ftw.raven.egg-info/dependency_links.txt
ftw.raven.egg-info/entry_points.txt
ftw.raven.egg-info/namespace_packages.txt
ftw.raven.egg-info/not-zip-safe
ftw.raven.egg-info/requires.txt
ftw.raven.egg-info/top_level.txt
ftw/raven/__init__.py
ftw/raven/client.py
ftw/raven/config.py
ftw/raven/configure.zcml
ftw/raven/monkeypatches.py
ftw/raven/reporter.py
ftw/raven/testing.py
ftw/raven/Extensions/install.py
ftw/raven/browser/__init__.py
ftw/raven/browser/configure.zcml
ftw/raven/browser/demo.py
ftw/raven/browser/javascript.py
ftw/raven/browser/resources/raven-integration.js
ftw/raven/browser/resources/raven.min.js
ftw/raven/demo/__init__.py
ftw/raven/demo/configure.zcml
ftw/raven/demo/views.py
ftw/raven/profiles/default/jsregistry.xml
ftw/raven/profiles/default/metadata.xml
ftw/raven/profiles/default_plone5/metadata.xml
ftw/raven/profiles/default_plone5/registry.xml
ftw/raven/profiles/uninstall/jsregistry.xml
ftw/raven/profiles/uninstall_plone5/registry.xml
ftw/raven/tests/__init__.py
ftw/raven/tests/client_mock.py
ftw/raven/tests/test_client.py
ftw/raven/tests/test_config.py
ftw/raven/tests/test_demo.py
ftw/raven/tests/test_integration.py
ftw/raven/tests/test_javascript.py
ftw/raven/tests/test_reporter.py
ftw/raven/tests/test_uninstall.py
ftw/raven/upgrades/__init__.py
ftw/raven/upgrades/20160120141654_seperate_lib_and_config_javascripts/__init__.py
ftw/raven/upgrades/20160120141654_seperate_lib_and_config_javascripts/jsregistry.xml
ftw/raven/upgrades/20160120141654_seperate_lib_and_config_javascripts/upgrade.py